[
  /* Spaceship Parts */

	// Must be transported to the Capital for launch.
	// Can be destroyed by any hostile military unit walking in their tile.
	{
		"name": "SS Booster",
		"unitType": "Civilian",
		"movement": 2,
		"cost": 750,
		"requiredTech": "Advanced Ballistics",
		"requiredResource": "Aluminum",
		"uniques": ["Spaceship part", "Cannot be purchased", "Only available <if [Apollo Program] is constructed>", "Uncapturable", "Can be added to [The Spaceship] in the Capital", "Limited to [6] per Civilization"]
		// costs 1500 in BNW
	},
	{
		"name": "SS Cockpit",
		"unitType": "Civilian",
		"movement": 2,
		"cost": 750,
		"requiredTech": "Satellites",
		"requiredResource": "Aluminum",
		"uniques": ["Spaceship part", "Cannot be purchased", "Only available <if [Apollo Program] is constructed>", "Uncapturable", "Can be added to [The Spaceship] in the Capital", "Limited to [2] per Civilization"]
		// costs 1500 in BNW
	},
	{
		"name": "SS Engine",
		"unitType": "Civilian",
		"movement": 1,
		"cost": 1750,
		"requiredTech": "Particle Physics",
		"uniques": ["Spaceship part","Consumes [2] [Aluminum]", "Cannot be purchased", "Only available <if [Apollo Program] is constructed>", "Uncapturable", "Can be added to [The Spaceship] in the Capital", "Limited to [2] per Civilization"]
		// costs 1500 in BNW
	},
	{
		"name": "SS Stasis Chamber",
		"unitType": "Civilian",
		"movement": 2,
		"cost": 750,
		"requiredTech": "Nanotechnology",
		"requiredResource": "Aluminum",
		"uniques": ["Spaceship part", "Cannot be purchased", "Only available <if [Apollo Program] is constructed>", "Uncapturable", "Can be added to [The Spaceship] in the Capital", "Limited to [2] per Civilization"]
		// costs 1500 in BNW
	}
]
